client/__init__.py
client/client.py
common/__init__.py
common/enums.py
common/environment.py
common/xai_uris.py
common/config/.env.local
common/config/.env.testing
core/__init__.py
core/project.py
core/usage_control.py
core/workspace.py
core/xai.py
arya_xai-0.0.15.dist-info/LICENSE
arya_xai-0.0.15.dist-info/METADATA
arya_xai-0.0.15.dist-info/WHEEL
arya_xai-0.0.15.dist-info/top_level.txt
arya_xai-0.0.15.dist-info/RECORD
