Metadata-Version: 2.1
Name: arya-xai
Version: 0.0.15
Summary: Full stack ML Observability with AryaXAI
License: MIT
Project-URL: Documentation, https://xai.arya.ai/docs/introduction
Keywords: arya-xai,ML observability
Classifier: Intended Audience :: Developers
Classifier: Intended Audience :: Science/Research
Classifier: Programming Language :: Python :: 3
Classifier: License :: OSI Approved :: MIT License
Classifier: Operating System :: OS Independent
Requires-Python: >=3.0
License-File: LICENSE
Requires-Dist: pydantic ==2.4.2
Requires-Dist: pyjwt ==2.8.0
